setup.py
Funniest_Manohar/__init__.py
Funniest_Manohar/text.py
Funniest_Manohar.egg-info/PKG-INFO
Funniest_Manohar.egg-info/SOURCES.txt
Funniest_Manohar.egg-info/dependency_links.txt
Funniest_Manohar.egg-info/not-zip-safe
Funniest_Manohar.egg-info/top_level.txt