Metadata-Version: 1.0
Name: Funniest-Manohar
Version: 0.1
Summary: The funniest joke in the world
Home-page: UNKNOWN
Author: Manohar Kowthavarapu
Author-email: mailme.manu31@gmail.com
License: MIT
Platform: UNKNOWN
